{
    "avg": {
        "wmc": 7.05,
        "ccn": 3.95,
        "bugs": 0.1,
        "kanDefect": 0.27,
        "relativeSystemComplexity": 161.27,
        "relativeDataComplexity": 0.7,
        "relativeStructuralComplexity": 160.56,
        "volume": 297.72,
        "commentWeight": 38.62,
        "intelligentContent": 74.69,
        "lcom": 2.35,
        "instability": 0.76,
        "afferentCoupling": 1.67,
        "efferentCoupling": 3.91,
        "difficulty": 4.51,
        "mi": 93.89,
        "distance": 0.17,
        "incomingCDep": 9.67,
        "incomingPDep": 1.33,
        "outgoingCDep": 15.73,
        "outgoingPDep": 5.33,
        "classesPerPackage": 10.2
    },
    "sum": {
        "loc": 8406,
        "cloc": 3633,
        "lloc": 4773,
        "nbMethods": 628,
        "nbClasses": 153,
        "nbInterfaces": 0,
        "nbPackages": 15,
        "violations": {
            "total": 20,
            "information": 0,
            "warning": 11,
            "error": 9,
            "critical": 0
        }
    }
}